wagtail_translatableforms/__init__.py
wagtail_translatableforms/apps.py
wagtail_translatableforms/blocks.py
wagtail_translatableforms/migrations/0001_initial.py
wagtail_translatableforms/migrations/__init__.py
wagtail_translatableforms/models.py
wagtail_translatableforms/serializers.py
wagtail_translatableforms/templates/customforms/confirm_delete.html
wagtail_translatableforms/templates/customforms/index.html
wagtail_translatableforms/templates/customforms/index_submissions.html
wagtail_translatableforms/templates/customforms/result_list.html
wagtail_translatableforms/templatetags/__init__.py
wagtail_translatableforms/templatetags/custom_tags.py
wagtail_translatableforms/urls.py
wagtail_translatableforms/utils.py
wagtail_translatableforms/views.py
wagtail_translatableforms-0.1.5.dist-info/LICENSE
wagtail_translatableforms-0.1.5.dist-info/METADATA
wagtail_translatableforms-0.1.5.dist-info/WHEEL
wagtail_translatableforms-0.1.5.dist-info/RECORD
