Metadata-Version: 2.1
Name: wagtail_translatableforms
Version: 0.1.5
Summary: Add translatableforms to wagtail projects
Home-page: https://github.com/BenderEg/wagtail-translatableforms
License: MIT
Author: Egor Nikitin
Author-email: eanikitin90@gmail.com
Requires-Python: >=3.11
Classifier: License :: OSI Approved :: MIT License
Classifier: Programming Language :: Python :: 3
Classifier: Programming Language :: Python :: 3.11
Classifier: Programming Language :: Python :: 3.12
Requires-Dist: django (>=4.2.11,<5.0.0)
Requires-Dist: djangorestframework (>=3.15.0,<4.0.0)
Requires-Dist: drf_spectacular (>=0.27.1,<0.28.0)
Requires-Dist: wagtail (>=5.2.3,<6.0.0)
Requires-Dist: wagtail-localize (>=1.8.2,<2.0.0)
Requires-Dist: wagtail-modeladmin (>=2.0.0,<3.0.0)
Requires-Dist: wagtailstreamforms (>=4.1.0,<5.0.0)
